unified_range/__init__.py
unified_range/api.py
unified_range/models.py
unified_range/utils.py
unified_range-0.1.1.dist-info/LICENSE
unified_range-0.1.1.dist-info/WHEEL
unified_range-0.1.1.dist-info/METADATA
unified_range-0.1.1.dist-info/RECORD
