Metadata-Version: 2.1
Name: unified-range
Version: 0.1.1
Summary: Convert between semver range and maven version range
Home-page: https://github.com/snyk/unified-range
License: MIT
Author: Snyk
Requires-Python: >=3.6,<4.0
Classifier: License :: OSI Approved :: MIT License
Classifier: Operating System :: OS Independent
Classifier: Programming Language :: Python :: 3
Classifier: Programming Language :: Python :: 3.10
Classifier: Programming Language :: Python :: 3.6
Classifier: Programming Language :: Python :: 3.7
Classifier: Programming Language :: Python :: 3.8
Classifier: Programming Language :: Python :: 3.9
Project-URL: Repository, https://github.com/snyk/unified-range
